<?xml version="1.0" encoding="UTF-8"?>
<objects serializationModel="Studio.01.10.00">
    <object class="AudioFile" id="{bc759c5f-304b-4788-8da9-757d788f641b}">
        <property name="assetPath">
            <value>01-308_PiuuAllumage.wav</value>
        </property>
        <property name="frequencyInKHz">
            <value>44.0999985</value>
        </property>
        <property name="channelCount">
            <value>2</value>
        </property>
        <property name="length">
            <value>1.5</value>
        </property>
        <relationship name="masterAssetFolder">
            <destination>{2b4fe14b-a6fa-4577-b106-d641d8433093}</destination>
        </relationship>
    </object>
</objects>
